Metadata-Version: 1.0
Name: copy-excel-format
Version: 0.1.9
Summary: copy excel format
Home-page: https://github.com/laplaciannin102/copy_excel_format
Author: Kosuke Asada
Author-email: laplaciannin102@gmail.com
License: Copyright (c) 2021, Kosuke Asada
